{
  "todos": [
    {
      "title": "",
      "createdAt": "2022-11-19T17:44:15.761Z",
      "lastUpdatedAt": "2022-11-19T18:32:30.073Z",
      "id": 2,
      "details": "gregdcdcfas",
      "date": "2022-11-19T18:32:24.655Z",
      "time": "2022-11-19T18:32:27.000Z"
    },
    {
      "title": "sdwdwdwewfreg",
      "createdAt": "2022-11-19T17:44:16.045Z",
      "lastUpdatedAt": "2022-11-19T17:47:34.708Z",
      "id": 3,
      "details": "abcd"
    },
    {
      "title": "",
      "createdAt": "2022-11-19T17:58:52.416Z",
      "lastUpdatedAt": "2022-11-19T17:58:52.416Z",
      "id": 4,
      "date": "2022-11-19T17:58:57.909Z",
      "time": "2022-11-19T17:59:00.957Z"
    },
    {
      "title": "",
      "createdAt": "2022-11-19T17:58:52.745Z",
      "lastUpdatedAt": "2022-11-19T17:58:52.745Z",
      "id": 5
    },
    {
      "title": "",
      "createdAt": "2022-11-19T17:58:52.878Z",
      "lastUpdatedAt": "2022-11-19T17:58:52.878Z",
      "id": 6
    },
    {
      "title": "",
      "createdAt": "2022-11-19T17:58:53.011Z",
      "lastUpdatedAt": "2022-11-19T17:58:53.011Z",
      "id": 7
    },
    {
      "title": "",
      "createdAt": "2022-11-19T17:58:53.130Z",
      "lastUpdatedAt": "2022-11-19T17:58:53.130Z",
      "id": 8
    },
    {
      "title": "",
      "createdAt": "2022-11-19T17:59:16.775Z",
      "lastUpdatedAt": "2022-11-19T17:59:16.775Z",
      "id": 9
    },
    {
      "title": "",
      "createdAt": "2022-11-19T17:59:17.189Z",
      "lastUpdatedAt": "2022-11-19T17:59:17.189Z",
      "id": 10
    },
    {
      "title": "",
      "createdAt": "2022-11-19T17:59:17.313Z",
      "lastUpdatedAt": "2022-11-19T17:59:17.313Z",
      "id": 11,
      "completed": false
    },
    {
      "title": "",
      "createdAt": "2022-11-19T17:59:17.445Z",
      "lastUpdatedAt": "2022-11-19T17:59:17.446Z",
      "id": 12
    },
    {
      "title": "",
      "createdAt": "2022-11-19T17:59:17.565Z",
      "lastUpdatedAt": "2022-11-19T17:59:17.565Z",
      "id": 13
    },
    {
      "title": "",
      "createdAt": "2022-11-19T17:59:17.730Z",
      "lastUpdatedAt": "2022-11-19T17:59:17.730Z",
      "id": 14
    },
    {
      "title": "",
      "createdAt": "2022-11-19T17:59:17.908Z",
      "lastUpdatedAt": "2022-11-19T17:59:17.908Z",
      "id": 15
    },
    {
      "title": "",
      "createdAt": "2022-11-19T17:59:18.058Z",
      "lastUpdatedAt": "2022-11-19T17:59:18.058Z",
      "id": 16
    },
    {
      "title": "",
      "createdAt": "2022-11-19T17:59:18.208Z",
      "lastUpdatedAt": "2022-11-19T17:59:18.208Z",
      "id": 17
    },
    {
      "title": "",
      "createdAt": "2022-11-19T17:59:18.356Z",
      "lastUpdatedAt": "2022-11-19T17:59:18.356Z",
      "id": 18
    },
    {
      "title": "",
      "createdAt": "2022-11-19T17:59:18.506Z",
      "lastUpdatedAt": "2022-11-19T17:59:18.506Z",
      "id": 19
    },
    {
      "title": "",
      "createdAt": "2022-11-19T17:59:18.643Z",
      "lastUpdatedAt": "2022-11-19T17:59:18.643Z",
      "id": 20
    },
    {
      "title": "",
      "createdAt": "2022-11-19T17:59:18.793Z",
      "lastUpdatedAt": "2022-11-19T17:59:18.793Z",
      "id": 21
    },
    {
      "title": "",
      "createdAt": "2022-11-19T17:59:18.914Z",
      "lastUpdatedAt": "2022-11-19T17:59:18.914Z",
      "id": 22
    },
    {
      "title": "",
      "createdAt": "2022-11-19T19:41:31.938Z",
      "lastUpdatedAt": "2022-11-19T19:41:31.938Z",
      "id": 23
    }
  ]
}